testeroozz/__init__.py
testeroozz/logg.py
testeroozz/sum_module.py
testeroozz-0.8.data/scripts/additional_script
testeroozz-0.8.data/scripts/script1
testeroozz-0.8.data/scripts/script1.py
testeroozz-0.8.dist-info/METADATA
testeroozz-0.8.dist-info/WHEEL
testeroozz-0.8.dist-info/top_level.txt
testeroozz-0.8.dist-info/RECORD
