Metadata-Version: 2.1
Name: testeroozz
Version: 0.8
Summary: this be a simplez testeroozz
Home-page: UNKNOWN
Author: ilja
Author-email: testeroozz@gmail.com
License: UNKNOWN
Platform: UNKNOWN
Requires-Dist: nose
